detaxa/__init__.py
detaxa/__main__.py
detaxa/taxonomy.py
detaxa/taxonomy_db/major_level_to_abbr.json
detaxa-0.6.1.dist-info/licenses/LICENSE
detaxa-0.6.1.dist-info/METADATA
detaxa-0.6.1.dist-info/WHEEL
detaxa-0.6.1.dist-info/entry_points.txt
detaxa-0.6.1.dist-info/top_level.txt
detaxa-0.6.1.dist-info/RECORD
