Metadata-Version: 2.4
Name: detaxa
Version: 0.6.1
Summary: NCBI taxonomy and lineage lookup
Author-email: Paul Li <po-e@lanl.gov>
License: GPL-3.0-or-later
Project-URL: Homepage, https://github.com/poeli/detaxa
Project-URL: Repository, https://github.com/poeli/detaxa
Project-URL: Bug Tracker, https://github.com/poeli/detaxa/issues
Keywords: taxonomy,bioinformatics,tree
Classifier: Programming Language :: Python :: 3
Classifier: Programming Language :: Python :: 3.8
Classifier: Programming Language :: Python :: 3.9
Classifier: Programming Language :: Python :: 3.10
Classifier: Programming Language :: Python :: 3.11
Classifier: Programming Language :: Python :: 3.12
Classifier: Intended Audience :: Science/Research
Classifier: Topic :: Scientific/Engineering :: Bio-Informatics
Classifier: Operating System :: OS Independent
Classifier: Development Status :: 4 - Beta
Requires-Python: >=3.8
License-File: LICENSE
Requires-Dist: click
Requires-Dist: requests
Requires-Dist: pandas
Provides-Extra: dev
Requires-Dist: pytest>=6.0; extra == "dev"
Requires-Dist: pytest-cov; extra == "dev"
Requires-Dist: black; extra == "dev"
Requires-Dist: flake8; extra == "dev"
Requires-Dist: mypy; extra == "dev"
Provides-Extra: test
Requires-Dist: pytest>=6.0; extra == "test"
Requires-Dist: pytest-cov; extra == "test"
Dynamic: license-file
